sentry_dingtalk_notify/__init__.py
sentry_dingtalk_notify/plugin.py
sentry_dingtalk_xm-1.2.1.dist-info/LICENSE
sentry_dingtalk_xm-1.2.1.dist-info/METADATA
sentry_dingtalk_xm-1.2.1.dist-info/WHEEL
sentry_dingtalk_xm-1.2.1.dist-info/entry_points.txt
sentry_dingtalk_xm-1.2.1.dist-info/top_level.txt
sentry_dingtalk_xm-1.2.1.dist-info/RECORD
