Metadata-Version: 2.1
Name: sentry-dingtalk-xm
Version: 1.2.1
Summary: A sentry extension integrates DingTalk robot webhook
Home-page: https://github.com/jiadaoyun/sentry-dingtalk-xm
Author: xm
Author-email: jiadaoyun@126.com
License: MIT
Keywords: sentry dingtalk
Platform: UNKNOWN
Classifier: License :: OSI Approved :: MIT License
Classifier: Programming Language :: Python
Classifier: Programming Language :: Python :: 3
Classifier: Programming Language :: Python :: 3.6
Classifier: Programming Language :: Python :: 3.7
Classifier: Programming Language :: Python :: Implementation :: CPython
Requires-Python: >=3.6.13
License-File: LICENSE
Requires-Dist: sentry (>=21.5.1)
